{
  "questions": [
    {
      "id": 1,
      "question": "Jimmy, 35 ans, est expulsé de son logement et n’a personne chez qui aller. Quelle structure peut l’héberger pour plusieurs mois avec accompagnement social ?",
      "options": [
        "Maison d’accueil",
        "Abri de nuit",
        "AIS",
        "CSS"
      ],
      "correct_answer": 0,
      "explanation": "Les maisons d’accueil offrent un hébergement temporaire (jusqu’à 275 jours) avec accompagnement social pour personnes sans logement."
    },
    {
      "id": 2,
      "question": "Une personne sans-abri est délogée d’un squat par la police et doit dormir quelque part la nuit suivante. Où peut-elle aller ?",
      "options": [
        "Abri de nuit",
        "Maison d’accueil",
        "AIS",
        "CSS"
      ],
      "correct_answer": 0,
      "explanation": "Les abris de nuit accueillent gratuitement les personnes sans-abri pour une nuit, souvent en période hivernale."
    },
    {
      "id": 3,
      "question": "Un propriétaire souhaite louer son bien sans craindre les impayés. Vers quelle structure peut-il se tourner ?",
      "options": [
        "AIS",
        "SLSP",
        "Forem",
        "MASS"
      ],
      "correct_answer": 0,
      "explanation": "Les Agences Immobilières Sociales gèrent des logements privés à loyers modérés pour les mettre à disposition de ménages précarisés."
    },
    {
      "id": 4,
      "question": "Une famille vit depuis 10 ans dans un camping résidentiel. Quelle mesure régionale vise leur relogement progressif ?",
      "options": [
        "Plan HP",
        "Housing First",
        "ADeL",
        "MIRE"
      ],
      "correct_answer": 0,
      "explanation": "Le Plan Habitat Permanent vise à reloger durablement les personnes vivant dans des campings résidentiels."
    },
    {
      "id": 5,
      "question": "Une famille sans-abri obtient un logement directement, avant tout accompagnement. Quelle approche est utilisée ?",
      "options": [
        "Housing First",
        "Maison d’accueil",
        "SLSP",
        "AIS"
      ],
      "correct_answer": 0,
      "explanation": "Le dispositif Housing First reloge immédiatement les sans-abri en logement ordinaire, avec accompagnement social."
    },
    {
      "id": 6,
      "question": "Un couple avec 4 enfants veut acheter une maison et cherche un prêt social. Quel organisme contacter ?",
      "options": [
        "FLFNW",
        "ONEM",
        "SWCS",
        "AIS"
      ],
      "correct_answer": 0,
      "explanation": "Le Fonds du Logement des Familles Nombreuses de Wallonie propose des prêts sociaux adaptés aux familles nombreuses."
    },
    {
      "id": 7,
      "question": "Une mère sortant de maison d’accueil veut louer un logement privé. Quelle aide financière peut-elle demander ?",
      "options": [
        "ADeL",
        "Plan HP",
        "Rénopack",
        "SECAL"
      ],
      "correct_answer": 0,
      "explanation": "L’Allocation de Déménagement et de Loyer (ADeL) aide à quitter un logement inadéquat et à payer le nouveau loyer."
    },
    {
      "id": 8,
      "question": "Un locataire souhaite rénover énergétiquement sa maison avec un prêt à 0 %. Quelle solution ?",
      "options": [
        "Rénopack (SWCS)",
        "ADeL",
        "Plan HP",
        "AIS"
      ],
      "correct_answer": 0,
      "explanation": "Le Rénopack, géré par la SWCS, est un prêt à 0 % pour financer des travaux de rénovation énergétique."
    },
    {
      "id": 9,
      "question": "Un jeune couple achète une maison et veut un crédit social pour la rénover. Vers qui se tourner ?",
      "options": [
        "SWCS",
        "FLFNW",
        "ONEM",
        "AIS"
      ],
      "correct_answer": 0,
      "explanation": ""
    },
    {
      "id": 10,
      "question": "Une famille nombreuse recherche un logement social adapté. Vers quelle institution publique se tourner ?",
      "options": [
        "SLSP",
        "AIS",
        "SWCS",
        "MASS"
      ],
      "correct_answer": 0,
      "explanation": "Les Sociétés de Logement de Service Public mettent en location des logements sociaux à loyers adaptés."
    },
    {
      "id": 11,
      "question": "Un élève présente des problèmes de vue lors d’un bilan scolaire. Quel service est compétent ?",
      "options": [
        "PSE",
        "SECAL",
        "SIS",
        "SWCS"
      ],
      "correct_answer": 0,
      "explanation": "Les Services de Promotion de la Santé à l’École assurent bilans de santé, dépistages et vaccinations des élèves."
    },
    {
      "id": 12,
      "question": "Un patient atteint d’une maladie incurable souhaite un accompagnement global en fin de vie. Vers quel dispositif se tourner ?",
      "options": [
        "Soins palliatifs",
        "CSS",
        "PSE",
        "IFAPME"
      ],
      "correct_answer": 0,
      "explanation": "Les soins palliatifs visent la meilleure qualité de vie possible pour les personnes en fin de vie, avec accompagnement global."
    },
    {
      "id": 13,
      "question": "Un patient hospitalisé doit rentrer à domicile mais nécessite infirmier, kiné et aide familiale. Qui coordonne tout cela ?",
      "options": [
        "Centre de coordination des soins et de l’aide à domicile",
        "CSS",
        "CLPS",
        "SIS"
      ],
      "correct_answer": 0,
      "explanation": "Ces centres coordonnent les différents prestataires (infirmiers, aides familiales, kinés...) pour une prise en charge à domicile."
    },
    {
      "id": 14,
      "question": "Une personne âgée seule installe un système d’alerte pour prévenir en cas de chute. Quel service est sollicité ?",
      "options": [
        "Télévigilance",
        "PSE",
        "SAS",
        "SECAL"
      ],
      "correct_answer": 0,
      "explanation": "La télévigilance permet d’alerter rapidement les secours en cas de problème à domicile (chute, malaise)."
    },
    {
      "id": 15,
      "question": "Un voisin rend chaque jour service gratuitement à une personne âgée dépendante. Quel statut peut-il demander ?",
      "options": [
        "Aidant proche",
        "Volontaire civil",
        "Travailleur pair",
        "Case manager"
      ],
      "correct_answer": 0,
      "explanation": "Le statut d’aidant proche reconnaît la personne qui aide régulièrement et gratuitement un proche dépendant."
    },
    {
      "id": 16,
      "question": "Une personne dépendante aux drogues cherche un accueil sans condition avec suivi médical et social. Quelle structure est adaptée ?",
      "options": [
        "MASS",
        "CLPS",
        "CSS",
        "AIS"
      ],
      "correct_answer": 0,
      "explanation": "Les Maisons d’Accueil Socio-Sanitaires accueillent sans condition les personnes dépendantes aux drogues et offrent un suivi pluridisciplinaire."
    },
    {
      "id": 17,
      "question": "Un directeur d’école est averti d’une épidémie d’oreillons. Quel service doit-il contacter ?",
      "options": [
        "PSE",
        "SIS",
        "AIS",
        "SECAL"
      ],
      "correct_answer": 0,
      "explanation": "Les Services de Promotion de la Santé à l’École assurent bilans de santé, dépistages et vaccinations des élèves."
    },
    {
      "id": 18,
      "question": "Un citoyen souhaite développer un projet local de prévention santé. Quel centre peut l’accompagner ?",
      "options": [
        "CLPS",
        "ONEM",
        "SIS",
        "AIS"
      ],
      "correct_answer": 0,
      "explanation": "Les Centres Locaux de Promotion de la Santé soutiennent les projets de prévention et mettent à disposition des outils pédagogiques."
    },
    {
      "id": 19,
      "question": "Un patient Alzheimer nécessite coordination des soins médicaux et sociaux. Qui s’en occupe ?",
      "options": [
        "Case manager",
        "Aidant proche",
        "SECAL",
        "SIS"
      ],
      "correct_answer": 0,
      "explanation": "Le case manager coordonne le parcours de soins et d’aides pour les personnes en situations complexes (souvent maladies neurodégénératives)."
    },
    {
      "id": 20,
      "question": "Une famille en crise se rend dans un service mutualiste agréé pour accueil et accompagnement social. Lequel ?",
      "options": [
        "CSS",
        "MASS",
        "SECAL",
        "AIS"
      ],
      "correct_answer": 0,
      "explanation": "Les Centres de Service Social des mutuelles offrent un premier accueil, écoute et accompagnement social des familles en difficulté."
    },
    {
      "id": 21,
      "question": "Un demandeur d’emploi souhaite un accompagnement en Wallonie. Quel organisme public régional s’occupe de lui ?",
      "options": [
        "FOREM",
        "ONEM",
        "MIRE",
        "CISP"
      ],
      "correct_answer": 0,
      "explanation": "Le FOREM est le service public wallon de l’emploi et de la formation, il accompagne les demandeurs d’emploi."
    },
    {
      "id": 22,
      "question": "Un chômeur souhaite toucher des allocations de chômage. Quel organisme fédéral gère cela ?",
      "options": [
        "ONEM",
        "FOREM",
        "MIRE",
        "SWCS"
      ],
      "correct_answer": 0,
      "explanation": "L’ONEM est un organisme fédéral qui gère les allocations de chômage et contrôle les demandeurs."
    },
    {
      "id": 23,
      "question": "Un jeune de 16 ans veut suivre une formation alternance école + entreprise. Où s’inscrire ?",
      "options": [
        "CEFA",
        "CISP",
        "IFAPME",
        "PMS"
      ],
      "correct_answer": 0,
      "explanation": "Les Centres d’Éducation et de Formation en Alternance permettent aux jeunes de suivre une formation école + entreprise avec statut scolaire."
    },
    {
      "id": 24,
      "question": "Un adulte souhaite une formation qualifiante organisée par la Région (hors plein exercice). Où aller ?",
      "options": [
        "IFAPME",
        "PSE",
        "SECAL",
        "SRJ"
      ],
      "correct_answer": 0,
      "explanation": "L’IFAPME propose des formations qualifiantes en alternance pour adultes et jeunes, orientées vers les métiers et PME."
    },
    {
      "id": 25,
      "question": "Une personne très éloignée de l’emploi bénéficie de coaching intensif et stage. Par qui ?",
      "options": [
        "MIRE",
        "ONEM",
        "SWCS",
        "AIS"
      ],
      "correct_answer": 0,
      "explanation": "Les Missions Régionales pour l’Emploi accompagnent intensivement les publics très éloignés du marché du travail."
    },
    {
      "id": 26,
      "question": "Une personne peu scolarisée suit des cours d’alphabétisation pour travailler. Dans quelle structure ?",
      "options": [
        "CISP",
        "PMS",
        "PSE",
        "SRJ"
      ],
      "correct_answer": 0,
      "explanation": "Les Centres d’Insertion Socioprofessionnelle forment et accompagnent des publics fragilisés vers le marché du travail."
    },
    {
      "id": 27,
      "question": "Un quartier défavorisé met en place des chantiers collectifs avec insertion. Quelle structure ?",
      "options": [
        "Régie de quartier",
        "SLSP",
        "AIS",
        "SECAL"
      ],
      "correct_answer": 0,
      "explanation": "Les régies de quartier favorisent la cohésion sociale par des chantiers et l’insertion par l’activité économique locale."
    },
    {
      "id": 28,
      "question": "Une personne en insertion travaille directement dans une entreprise sociale adaptée. Quelle structure ?",
      "options": [
        "Entreprise d’insertion",
        "ETA",
        "SLSP",
        "PSE"
      ],
      "correct_answer": 0,
      "explanation": "Les entreprises d’insertion emploient directement des personnes éloignées de l’emploi dans l’économie sociale."
    },
    {
      "id": 29,
      "question": "Un citoyen veut des infos sur métiers et formations. Où peut-il aller ?",
      "options": [
        "Carrefour/Cité des métiers",
        "MASS",
        "AIS",
        "CSS"
      ],
      "correct_answer": 0,
      "explanation": "Les Cités des métiers offrent information et orientation sur les métiers, formations et parcours pro."
    },
    {
      "id": 30,
      "question": "Un CPAS oriente un demandeur vers un atelier CV et offres locales. Où ?",
      "options": [
        "Maison de l’emploi",
        "MIRE",
        "SAS",
        "PSE"
      ],
      "correct_answer": 0,
      "explanation": "Les maisons de l’emploi organisent ateliers CV, orientation et offres locales pour les demandeurs."
    },
    {
      "id": 31,
      "question": "Un enfant primo-arrivant doit apprendre intensivement le français pour s’intégrer. Où est-il orienté ?",
      "options": [
        "DASPA",
        "FLA",
        "CEFA",
        "SAS"
      ],
      "correct_answer": 0,
      "explanation": "Le Dispositif d’Accueil et de Scolarisation des Primo-Arrivants propose un apprentissage intensif du français et une intégration scolaire."
    },
    {
      "id": 32,
      "question": "Un élève non francophone en école ordinaire reçoit un soutien linguistique. Quel dispositif ?",
      "options": [
        "FLA",
        "DASPA",
        "PSE",
        "PMS"
      ],
      "correct_answer": 0,
      "explanation": "Le Français Langue d’Apprentissage soutient les élèves non francophones dans les classes ordinaires."
    },
    {
      "id": 33,
      "question": "Une élève décrocheuse bénéficie d’un plan personnalisé dans son école. Quel dispositif ?",
      "options": [
        "DIAS",
        "SAS",
        "PSE",
        "PMS"
      ],
      "correct_answer": 0,
      "explanation": "Le Dispositif Interne d’Accrochage Scolaire propose un plan personnalisé pour les élèves décrocheurs."
    },
    {
      "id": 34,
      "question": "Un jeune en rupture est accueilli temporairement pour réintégrer l’école. Où ?",
      "options": [
        "SAS",
        "DIAS",
        "MASS",
        "CSS"
      ],
      "correct_answer": 0,
      "explanation": "Les Services d’Accrochage Scolaire accueillent temporairement les jeunes en rupture pour favoriser la réintégration scolaire."
    },
    {
      "id": 35,
      "question": "Un enfant en difficulté est orienté vers une aide psychologique et sociale scolaire. Où ?",
      "options": [
        "PMS",
        "PSE",
        "AIS",
        "SECAL"
      ],
      "correct_answer": 0,
      "explanation": "Les Centres Psycho-Médico-Sociaux accompagnent élèves et familles sur le plan psychologique, social et orientation scolaire."
    },
    {
      "id": 36,
      "question": "Des intervenants extérieurs neutres préviennent les conflits et violences dans une école. Quel dispositif ?",
      "options": [
        "Médiation scolaire",
        "SAS",
        "SECAL",
        "MIRE"
      ],
      "correct_answer": 0,
      "explanation": "La médiation scolaire vise à prévenir et résoudre les conflits en milieu scolaire, lutter contre le décrochage."
    },
    {
      "id": 37,
      "question": "Une équipe intervient en urgence dans une école après un suicide. Qui ?",
      "options": [
        "Équipe mobile",
        "PSE",
        "SIS",
        "AIS"
      ],
      "correct_answer": 0,
      "explanation": "Les équipes mobiles interviennent en urgence dans les écoles lors de crises (suicide, drame, violence)."
    },
    {
      "id": 38,
      "question": "Un jeune suit école + entreprise avec statut scolaire. Où ?",
      "options": [
        "CEFA",
        "IFAPME",
        "CISP",
        "SIS"
      ],
      "correct_answer": 0,
      "explanation": "Les Centres d’Éducation et de Formation en Alternance permettent aux jeunes de suivre une formation école + entreprise avec statut scolaire."
    },
    {
      "id": 39,
      "question": "Un jeune apprend un métier en alternance dans une PME. Quel organisme ?",
      "options": [
        "IFAPME",
        "CEFA",
        "MIRE",
        "SECAL"
      ],
      "correct_answer": 0,
      "explanation": "L’IFAPME propose des formations qualifiantes en alternance pour adultes et jeunes, orientées vers les métiers et PME."
    },
    {
      "id": 40,
      "question": "Un enfant va dans une école de devoirs après les cours. Quelle mission ?",
      "options": [
        "École de devoirs",
        "SAS",
        "PMS",
        "PSE"
      ],
      "correct_answer": 0,
      "explanation": ""
    },
    {
      "id": 41,
      "question": "Un jeune adulte handicapé suit une formation pratique adaptée. Où ?",
      "options": [
        "CFISPA",
        "CISP",
        "CEFA",
        "MASS"
      ],
      "correct_answer": 0,
      "explanation": "Les Centres de Formation et d’Insertion Socioprofessionnelle Adaptée forment les personnes handicapées à des métiers adaptés."
    },
    {
      "id": 42,
      "question": "Un travailleur handicapé trouve un emploi adapté avec encadrement. Dans quelle structure ?",
      "options": [
        "ETA",
        "Entreprise d’insertion",
        "SAS",
        "SIS"
      ],
      "correct_answer": 0,
      "explanation": "Les Entreprises de Travail Adapté emploient des personnes handicapées dans un environnement adapté et encadré."
    },
    {
      "id": 43,
      "question": "Une famille veut maintenir le lien entre un enfant et son père dans un lieu neutre. Quelle structure ?",
      "options": [
        "Espaces-Rencontres",
        "SECAL",
        "PMS",
        "AIS"
      ],
      "correct_answer": 0,
      "explanation": "Les Espaces-Rencontres permettent de maintenir ou restaurer le lien parent-enfant dans un lieu neutre et supervisé."
    },
    {
      "id": 44,
      "question": "Une femme victime de violences conjugales est accueillie et soutenue juridiquement. Quel service ?",
      "options": [
        "Service spécialisé violences",
        "SECAL",
        "PSE",
        "ONEM"
      ],
      "correct_answer": 0,
      "explanation": "Ces services accompagnent les victimes de violences conjugales (soutien, juridique, psy) et travaillent aussi avec les auteurs."
    },
    {
      "id": 45,
      "question": "Un couple souhaite éviter un procès coûteux pour leur divorce. Qui peuvent-ils solliciter ?",
      "options": [
        "Médiation familiale",
        "SECAL",
        "CPAS",
        "ONEM"
      ],
      "correct_answer": 0,
      "explanation": "La médiation familiale aide les parents séparés à trouver des accords à l’amiable, sans passer par un procès long et coûteux."
    },
    {
      "id": 46,
      "question": "Une personne n’a pas reçu sa pension alimentaire depuis 6 mois. Qui peut l’aider à la récupérer ?",
      "options": [
        "SECAL",
        "CPAS",
        "SWCS",
        "AIS"
      ],
      "correct_answer": 0,
      "explanation": "Le Service des Créances Alimentaires récupère les pensions alimentaires impayées et peut avancer les sommes aux créanciers."
    },
    {
      "id": 47,
      "question": "Un adulte lourdement handicapé est accueilli le jour dans un service adapté. Où ?",
      "options": [
        "SAJA",
        "SAS",
        "SRJ",
        "SRA"
      ],
      "correct_answer": 0,
      "explanation": "Les Services d’Accueil de Jour pour Adultes accueillent des adultes handicapés non insérables en emploi pour activités adaptées."
    },
    {
      "id": 48,
      "question": "Un enfant handicapé non scolarisé participe à des activités adaptées de jour. Où ?",
      "options": [
        "SAS’J",
        "SAS",
        "DIAS",
        "CFISPA"
      ],
      "correct_answer": 0,
      "explanation": "Les Services d’Accueil Spécialisés pour Jeunes accueillent des jeunes handicapés non scolarisés pour activités éducatives adaptées."
    },
    {
      "id": 49,
      "question": "Un adulte handicapé vit en logement supervisé avec accompagnement vers autonomie. Quelle structure ?",
      "options": [
        "Service logement supervisé (AVIQ)",
        "Maison d’accueil",
        "SAS",
        "AIS"
      ],
      "correct_answer": 0,
      "explanation": "Le logement supervisé prépare les personnes handicapées à la vie autonome avec suivi éducatif et social."
    },
    {
      "id": 50,
      "question": "Une commune met en place un agent pour informer localement les personnes handicapées. Comment s’appelle-t-il ?",
      "options": [
        "Handicontact",
        "CSS",
        "SIS",
        "MASS"
      ],
      "correct_answer": 0,
      "explanation": "L’agent Handicontact informe localement les personnes handicapées et les oriente vers les services compétents."
    }
  ]
}